[
    {
        "name": "John Doe",
        "age": 25,
        "gender": "male",
        "skills": [
            "PHP",
            "MySQL",
            "JavaScript"
        ],
        "isMarried": false,
        "weight": 75.5
    },
    {
        "name": "Jane Doe",
        "age": 21,
        "gender": "female",
        "skills": [
            "PHP",
            "MySQL",
            "JavaScript"
        ],
        "isMarried": true,
        "weight": 50.5
    },
    {
        "name": "Marko",
        "age": 25,
        "gender": "male",
        "skills": [
            "PHP",
            "MySQL",
            "JavaScript"
        ],
        "isMarried": false,
        "weight": 80.5
    },
    {
        "name": "Marko",
        "age": 25,
        "gender": "male",
        "skills": [
            "PHP",
            "MySQL",
            "JavaScript"
        ],
        "isMarried": false,
        "weight": 80.5
    },
    {
        "name": "Marko",
        "age": 25,
        "gender": "male",
        "skills": [
            "PHP",
            "MySQL",
            "JavaScript"
        ],
        "isMarried": false,
        "weight": 80.5
    },
    {
        "name": "Marko",
        "age": 25,
        "gender": "male",
        "skills": [
            "PHP",
            "MySQL",
            "JavaScript"
        ],
        "isMarried": false,
        "weight": 80.5
    },
    {
        "name": "Marko",
        "age": 25,
        "gender": "male",
        "skills": [
            "PHP",
            "MySQL",
            "JavaScript"
        ],
        "isMarried": false,
        "weight": 80.5
    },
    {
        "name": "Marko",
        "age": 25,
        "gender": "male",
        "skills": [
            "PHP",
            "MySQL",
            "JavaScript"
        ],
        "isMarried": false,
        "weight": 80.5
    }
]